<?xml version="1.0" encoding="UTF-8" ?>
<language id="49">

<page id="2008" title="Script Object Commands" descr="0">
 <t id="830">ANARKIS_SETDOCKED</t>
 <t id="831">ANARKIS_SELLWARES</t>
 <t id="832">ANARKIS_BUYWARES</t>
 <t id="833">ANARKIS_DEFENSIVEWING</t>
 <t id="834">ANARKIS_ATTACKWING</t>
 <t id="835">ANARKIS_CLEANSECTOR</t>
 <t id="836">ANARKIS_DOCKALL</t>
 <t id="1231">ANARKIS_SETTACTICS</t>
 <t id="1232">ANARKIS_AUTOCARRIER</t>
 <t id="1131">ANARKIS_SETUPSTATION</t>
 <t id="1132">ANARKIS_STATIONDEFENSE</t>
</page>

<page id="2010" title="Script Cmd Names" descr="Long version of commandos. These are the commandos assigned to ships using the commandconsole. Page 2010 and 2011 belong together and hold short and long versions of the same commands"> 
 <t id="830">\033RAVS:\033X Heimatbasissetup</t>
 <t id="831">\033RAVS:\033X Verkaufe Waren...</t>
 <t id="832">\033RAVS:\033X Kaufe Waren für Träger...</t>
 <t id="833">\033RAVS:\033X Sende Verteidigungsgeschwader</t>
 <t id="834">\033RAVS:\033X Geschwaderangriff auf...</t>
 <t id="835">\033RAVS:\033X Räume Sektor</t>
 <t id="836">\033RAVS:\033X Alle Schiffe andocken</t>
 <t id="1231">\033RAVS:\033X Trägersetup</t>
 <t id="1232">\033RAVS:\033X Automatisierter Träger</t>
 <t id="1131">\033RAVS:\033X Verteidigungssystemsetup</t>
 <t id="1132">\033RAVS:\033X Sektorverteidigung</t>
</page> 

<page id="2011" title="Script Cmd Shorts" descr="Short version of commandos. These are the commandos assigned to ships using the commandconsole. Page 2010 and 2011 belong together and hold short and long versions of the same commands"> 
 <t id="830">set.homebase</t>  
 <t id="831">sell.ware</t>
 <t id="832">buy.ware</t>
 <t id="833">defense.wing</t>
 <t id="834">attack.wing</t>
 <t id="835">clean.sector</t>
 <t id="836">dock.ships</t>
 <t id="1131">set.defense</t>
 <t id="1132">auto.station</t>
 <t id="1231">set.tactics</t>
 <t id="1232">auto.carrier</t>
</page> 

<page id="2022"> 
 <t id="830">Erlaubt der ausgewählten Heimatbasis Einstellungen für die angedockten Jäger des Trägers. Schiffe werden umbenannt und Raketeneinstellungen zugewiesen.</t>  
 <t id="831">Schicke mehrere Schiffe zum verkauf der Waren des Trägers</t>
 <t id="832">Schicke mehrere Schiffe um eine bestimmte Anzahl an Waren von der nächstgelegenen Fabrik zu kaufen</t>
 <t id="833">Schickt ein Geschwader um den Träger oder ein anderes Schiff zu verteidigen</t>
 <t id="834">Schickt ein Geschwader zum Angriff gegen ein Schiff oder eine Fabrik</t>
 <t id="835">Befreit den Sektor von allen Feinden</t>
 <t id="836">Alle Schiffe die diese Heimatbasis eingestellt haben werden hier andocken. Weiter entfernte Schiffe die einen Sprungantrieb haben werden versuchen zum Träger zu springen.</t>
 <t id="1131">Setup von Anarkis Verteidigungsstation auf dieser Station.</t>
 <t id="1132">Aktiviert einen Verteidigungsmodus für diese Station. Sie wird Schiffe gegen Eindringlinge aussenden und gelandete Schiffe reparieren</t>
 <t id="1231">Dieser Befehl erlaubt das Setup der gelandeten Schiffe und des Trägers im automatisierten Modus.</t>
 <t id="1232">Automatisierter Modus. Der Träger wird sich selbst verteidigen und Schiffe bei Bedarf starten.</t>
</page> 

<page id="8510" title="ACC" descr="Anarkis Command Carrier">
 <t id="100">\033RAVS:\033X Anarkis Verteidigungssystem</t>
 <t id="101">265</t>
 <t id="102">Anarkis Federation</t>
 <t id="103">[author][b]Anarkis Federation[/b][/author][b]Anarkis Verteidigungssystem[/b] v%s erfolgreich installiert ! </t>
 <t id="104">[author][b]Anarkis Federation[/b][/author][b]Anarkis Verteidigungssystem[/b] erfolgreich aufgerüstet auf v%s !</t>
 <t id="105">[author][b]AVS - %s[/b][/author] Sie können diesen Befehl nicht auf ihrem Spielerschiff benutzen.</t>
 <t id="106">[author][b]Anarkis Federation[/b][/author][b]Anarkis Verteidigungssystem[/b] wurde entfernt.\nBitte speichern Sie nun ihr Spiel, beenden es und führen die Datei 'uninstall avs.bat' im X3 Verzeichnis aus.</t>
 
 <t id="200">Anarkis Trägermenü</t>

 <t id="210">Allgemein</t>
 <t id="211">Hangars ...</t>
 <t id="212">Trägerübersicht</t>
 <t id="213">Raketennutzung  \033R&lt;\033X \033Y%s\033X \033R&gt;\033X</t>
 <t id="214">Notsprung  \033R&lt;\033X \033Y%s\033X \033R&gt;\033X - Schildlimit  \033R&lt;\033X \033Y%s\033X \033R&gt;\033X</t>
 <t id="215">Autosprung  \033R&lt;\033X \033Y%s\033X \033R&gt;\033X - Minimale Reichweite  \033R&lt;\033X \033Y%s\033X \033R&gt;\033X</t>
 <t id="216">Treibstoffversorgungsmenge \(in Sprüngen\)  \033R&lt;\033X \033Y%s\033X \033R&gt;\033X</t>
 <t id="217">Setup der angedockten Schiffe</t>

 <t id="220">Setup für automatisierten Träger</t>
 <t id="221">\033WMinimale Gefahrenstufe\033X</t>
 <t id="222">\033WWarnmitteilungen anzeigen\033X</t>
 <t id="223">\033WBeschädigte Schiffe zum\033X</t>
 <t id="224">\033WAngriffsmodus\033X</t>
 <t id="225">\033WSchiffsanzahl für Verteidigung\033X</t>
 <t id="226">\033WRadar Reichweite\033X</t>
 <t id="227">Fraktionen ignorieren  \033R&lt;\033X \033Y%s\033X \033R&gt;\033X</t>
 <t id="228">Benachrichtigungen</t>
 <t id="229">\033WWarnungsart\033X</t>
  
 <t id="230">AVS Plugin Einstellungen</t>
 <t id="231">Einstellungen auf \033Yalle\033X angedockten Schiffe anwenden</t>
 <t id="232">Eistellungen auf Standardwerte zurücksetzen</t>
 <t id="233">Untertitel</t>
 <t id="234">Audio</t>
 <t id="235">Popup</t>
 <t id="236">Debug Logfile Output  \033R&lt;\033X \033Y%s\033X \033R&gt;\033X</t>
 <t id="237">Einstellungen nur auf alle \033Yaktiven\033X angedockten Schiffe anwenden</t>
 <t id="238">Verzögerung bevor eingesetzte Jäger andocken sollen \033R&lt;\033X \033Y%s sek\033X \033R&gt;\033X</t>
 
 <t id="240">Trägermanagement</t>
 <t id="241">Automatisierter Träger ...</t>
 <t id="242">Reparaturbuchten ...</t>
 <t id="243">Schiffsversorgung ...</t>
 <t id="244">Turmeinstellungen : \033Y%s\033X</t>
 <t id="245">Verteidige Schiff</t>
 <t id="246">Feinde angreifen</t>
 <t id="247">Raketenverteidigung</t>
 <t id="248">\033RMARS:\033X Offensiv</t>
 <t id="249">\033RMARS:\033X Defensiv</t>
 
 <t id="201">Aktiviert</t>
 <t id="202">Deaktiviert</t>
 <t id="203">Ja</t>
 <t id="204">Nein</t>
 <t id="205">Standard</t>
 <t id="206">Automatische Auswahl</t>
 <t id="207">Stärkster zuerst</t>
 <t id="208">Nächster zuerst</t>
 <t id="209">Kein</t>
 
 <t id="250">Träger : \033Y%s\033X [%s]</t>
 <t id="251">Standort : \033Y%s\033X</t>
 <t id="252">Angedockt : %s/%s - Besitzer : %s</t>
 <t id="260">© Serial Kicked / [\033YAnarkis Federation\033X]</t>
 
 <t id="300">Wähle die Anzahl an Schiffen die für Verteidigungszwecke genutzt werden sollen</t>
 <t id="301">Zielauswahlsetup</t>
 <t id="302">Wähle aus wie angreifende Schiffe gegnerische Schiffe auswählen sollen</t>
 <t id="303">Beschädigte Schiffe zurückziehen ?</t>
 <t id="304">Eine Warnmitteilung anzeigen wenn der Träger in Gefahr ist ?</t>
 <t id="305">Dieses Menü erlaubt die Auswahl was die minimale Gefahrenstufe ist welche den start der Jäger auslöst. Um zu verstehen wie dieses Stufensystem arbeitet musst du die "Gefahrenwerte" wissen die jeder Art von Schiff zugeordnet ist und du solltest auch wissen das der Träger immer Schiffe aussenden wird wenn ein gegnerischer M1/M2 gesichtet wurde. Kampfdrohnen werden ignoriert.</t>
 <t id="306">M5: 1 - M4: 2  - M3: 5 - M8: 10 - M6: 14 - M7: 35\nTL: 15 - TM: 8 - TP/TS: 2\n\n\n\n</t>
 <t id="307">Minimale Gefahrenstufe</t>
 <t id="308">Wähle die Treibstoffversorgungsmenge in Sprüngen</t>
 <t id="309">Soll das Autosprung-Feature bei allen angedockten Schiffen aktiviert werden ?</t>
 <t id="310">Lege die minimale Distanz für den Autosprung fest</t>
 <t id="311">Soll das Notsprung-Feature bei allen angedockten Schiffen aktiviert werden ?</t>
 <t id="312">Lege den Schwellenwert der Schilde in Prozent für den Notsprung fest</t>
 <t id="313">Lege die Raketennutzung in Prozent fest</t>
 <t id="314">Wähle eine neue Radarreichweite in Metern aus</t>
 <t id="315">Lege eine neue Landeverzögerung in Sekunden fest</t>
 
 <t id="400">Mechaniker</t>
 <t id="401">Man kann Mechaniker einstellen um beschädigte Jäger zu reparieren. In jedem freundlichen Sektor kann man Mechaniker für Geld anheuern. Außer Dienst kostet ein Mechaniker etwa 1000 Credits pro Stunde und mehr wenn sie ein Schiff reparieren. Je mehr Mechaniker man hat desto schneller laufen die Reparaturen.\n\nDerzeitige Kosten außer Dienst : \033Y%s Credits pro Stunde\033X\nDerzeitge Kosten bei Reparaturen : \033Y%s Credits pro Stunde\033X\n\n\n\n</t>
 <t id="402">Du hast derzeit : \033Y%s\033X Mechaniker (Kosten außer Dienst : \033Y%s\033X Credits pro Stunde)</t>
 <t id="403">Einstellungen</t>
 <t id="404">Angedockte Schiffe reparieren lassen  \033R&lt;\033X \033Y%s\033X \033R&gt;\033X</t>
 <t id="405">Den Träger reparieren lassen  \033R&lt;\033X \033Y%s\033X \033R&gt;\033X</t>
 <t id="406">Management : \033Y%s Mechaniker\033X</t>
 <t id="407">Neue Mechaniker einstellen</t>
 <t id="408">Mechaniker entlassen</t>
 <t id="409">Beschädigte Schiffe</t>
 <t id="410">  [%s] \033Y%s\033X - Hülle : %s/100</t>
 <t id="411">Das anheuern eines neuen Mechanikers kostet 50.0000 Credits. Sind sie sicher ?</t>
 <t id="412">Du hast nicht genug Geld um einen neuen Mechaniker einzustellen.</t>
 <t id="413">Du benötigst eine freundliche Handelsstation im aktuellen Sektor des Trägers.</t>

 <t id="420">Hangarmanagement</t>
 <t id="421">Wähle die Schiffe aus die von AVS Befehlen genutzt werden sollen</t>
 <t id="422">Liste der angedockten Schiffe</t>
 <t id="423">Allgemeine Befehle</t>
 <t id="424">Weise allen angedockten Schiffen die Heimatbasis zu</t>
 <t id="425">Management</t>
 <t id="426">Alle Schiffe hinzufügen</t>
 <t id="427">Nur M3 und M4 Schiffe hinzufügen</t>
 <t id="428">Nur M3 Schiffe hinzufügen</t>
 <t id="429">Alle Schiffe entfernen</t>
 <t id="430">  [%s] \033Y%s\033X - %s</t>
 <t id="431">\033GAktiv\033X</t>
 <t id="432">\033RInaktiv\033X</t>
 <t id="433">\033YWird repariert\033X</t>
 <t id="434">Angedockte Schiffe umbenennen</t>
 <t id="435">Heimatbasis nur den aktiven Schiffen zuweisen</t>

 <t id="440">Schiffsversorgung</t>
 <t id="441">Hier kann nun Fracht zwischen dem Träger und dessen angedockten Schiffen bewegt werden\n\n\n</t>
 <t id="442">Standardaktionen</t>
 <t id="443">Bewege Fracht vom Träger zu den angedockten Schiffen</t>
 <t id="444">Entlade Fracht in den Träger</t>
 <t id="445">Erweitert</t>
 <t id="446">Erlaube dem Träger zerstörte Jäger nachzukaufen  \033R&lt;\033X \033Y%s\033X \033R&gt;\033X</t>
 <t id="447">Erlaube dem Träger sich in der Schiffswerft zu reparieren  \033R&lt;\033X \033Y%s\033X \033R&gt;\033X</t>
 <t id="448">Erlaube dem Träger die Schiffe automatisch zu versorgen \033R&lt;\033X \033Y%s\033X \033R&gt;\033X</t>
 <t id="449">Dieses Menü erlaubt das bewegen von Waren von angedockten Schiffen zum Träger.\n\n</t>
 <t id="450">\033YEntlade :\033X %s</t>
 <t id="451">Nur Handelswaren [ausgenommen Energiezellen]</t>
 <t id="452">Nur Handelswaren [inklusive Energiezellen]</t>
 <t id="453">Raketen</t>
 <t id="454">Alles nicht ausgerüstet</t>
 <t id="455">\033YVon :\033X %s</t>
 <t id="456">Nur aktive Schiffe</t>
 <t id="457">Alle angedockten Schiffe</t>
 <t id="458">\033YÜberprüfen\033X</t>
 <t id="459">Aktion ausführen</t>
 
 <t id="460">Ignorierte Fraktionen</t>
 <t id="461">Manage</t>
 <t id="462">Liste löschen</t>
 <t id="463">Eine Fraktion zur Liste hinzufügen</t>
 <t id="464">\033Y%s\033X - entfernen</t>
 <t id="465">Wähle eine zu ignorierende Fraktion</t>

 <t id="480">Schiffe umbenennen</t>
 <t id="481">Shiffstyp Klasse - Nummer</t>
 <t id="482">Trägername - Schiffstyp - Nummer</t>
 <t id="483">Erbauerrasse Klasse - Nummer</t>
 <t id="484">Erlaubt das umbenennen aller angedockten Schiffe auf einmal.</t>
 <t id="485">Setup</t>
 <t id="486">Allen angedockten Schiffen zuweisen</t>
 <t id="487">Allen aktiven Schiffen zuweisen</t>
 <t id="488">\033YAusgewählt : \033X%s</t>
 <t id="489">\033YBeispiel : \033X%s</t>

 
 <t id="500">[author][b]Anarkis Trägerkommandos[/b][/author] [b]Warnung:[/b] Ihr [b]%s[/b] im Sektor [b]%s[/b] ist in Gefahr und benötigt ihre Aufmerksamkeit.</t>
 <t id="501">[author][b]Anarkis Trägerkommandos[/b][/author] [b]Abgebrochen:[/b] Für diesen Befehl haben Sie nicht genug Schiffe in %s</t>
 <t id="502">[author][b]Anarkis Trägerkommandos[/b][/author] [b]Abgebrochen:[/b] Zum räumen des Sektors haben Sie nicht genug Schiffe in %s. Mindestens 5 werden benötigt.</t>
 <t id="503">[author][b]Anarkis Trägerkommandos[/b][/author] [b]Fehler:[/b] Nicht genügend Waren im Frachtraum um ein Schiff auszurüsten.</t>
 <t id="504">[author][b]Anarkis Trägerkommandos[/b][/author] [b]Erfolgreich:[/b] %s hat %s/%s Schiffe mit %s %s ausgerüstet.</t>
 <t id="505">[author][b]Anarkis Trägerkommandos[/b][/author] [b]Abgebrochen:[/b] %s - Keine Station in Reichweite hat genügend %s.</t>
 <t id="506">\033RALARM:\033X \033W%s im Sektor %s benötigt Hilfe !\033X</t>
 
 <t id="520">Schiffe ausrüsten</t>
 <t id="521">\033YWaren\033X</t>
 <t id="522">&lt; \033Yneue Ware hinzufügen\033X &gt;</t>
 <t id="523">\033W%s\033X [Menge: %s]  &lt;\033Rentfernen\033X&gt;</t>
 <t id="524">\033YModus :\033X %s</t>
 <t id="525">Identische Warenmenge zu allen Schiffen</t>
 <t id="526">Festgelegte Warenmenge auf jedes Schiff</t>
 <t id="527">\033YZiel :\033X %s</t>
 <t id="528">Angedockten Schiffe</t>
 <t id="529">Aktive Schiffe</t>
 <t id="530">\033YÜberprüfen\033X</t>
 <t id="531">Aktion ausführen</t>
 <t id="532">Wähle die Ware aus die bewegt werden soll</t>
 <t id="533">Wähle die Menge</t>

 <t id="540">Transferbericht</t>
 <t id="541">Waren transferiert</t>
 <t id="542">\033W%s %s\033X transferiert zu \033Y%s\033X</t>
 <t id="543">\033W%s %s\033X entladen von \033Y%s\033X</t>
 
 <t id="600">\033RAVS:\033X Räume Sektor</t>
 <t id="601">\033RAVS:\033X Alle meine Schiffe andocken</t>
 <t id="602">\033RAVS:\033X Mein Ziel angreifen</t>
 <t id="603">\033RADS\033X \033WManager\033W</t>

 <t id="640">\033RAVS:\033X Verkaufe Waren</t>
 <t id="641">Ausgewählte Waren</t>
 <t id="642">Schnellauswahl</t>
 <t id="643">Liste löschen</t>
 <t id="644">Füge alle Handelswaren hinzu</t>
 <t id="645">Beginne Transfer</t>
 <t id="646">&lt; \033Yfüge neue Ware hinzu\033X &gt;</t>
 <t id="647">Einstellungen</t>
 <t id="648">Maximale Entfernung \033R&lt;\033X \033Y%s Sektoren\033X \033R&gt;\033X</t>
 <t id="649">Dieser Befehl erlaubt es dem Träger seine Waren mit Hilfe der angedockten Schiffe an umliegende Stationen zu verkaufen. Es gibt keine Überprüfung auf gegnerische Sektoren daher wähle die Entfernung vorsichtig.\n\n\n\n</t>
 <t id="650">\033W%s\033X - Anzahl: \033W%s\033X  &lt;\033Yentfernen\033X&gt;</t>
 <t id="651">Wähle die neue Sprungreichweite</t>
 <t id="652">Wähle eine Ware die hinzugefügt werden soll</t>
 <t id="653">\033R[AVS]\033X \033Y%s\033X verkauft \033Y%s\033X an \033Y%s\033X</t> 
 <t id="654">\033R[AVS]\033X Keine Station kauft \033Y%s\033X</t> 
 <t id="655">\033R[AVS]\033X Kein Schiff fähig \033Y%s\033X zu transportieren</t>
 <t id="656">\033R[AVS]\033X Keine Station in Reichweite verkauft \033Y%s\033X</t> 
 <t id="657">\033RAVS:\033X Kaufe Waren</t>
 <t id="658">Dieser Befehl erlaubt es dem Träger mit Hilfe der angedockten Schiffe Waren von umliegenden Stationen zu kaufen. Es gibt keine Überprüfung auf gegnerische Sektoren daher wähle die Entfernung vorsichtig.\n\n\n\n</t>
 <t id="659">fortfahren</t>
 <t id="660">\033W%s\033X - Menge: \033W%s\033X  &lt;\033Yentfernen\033X&gt;</t>
 <t id="661">\033R[AVS]\033X \033Y%s\033X kaufe \033Y%s %s\033X bei \033Y%s\033X</t> 
 <t id="662">Wähle die gewünschte Menge</t>
 <t id="663">Füge alle Raketenarten hinzu</t>
 
 <t id="700">\033R[AVS]\033X \033WGeschwader %s: \033X %s &lt;%s&gt;</t> 
 <t id="702">\033R[AVS]\033X %s - \033WRückzug...\033X</t>
 <t id="703">\033R[AVS]\033X %s</t>
 <t id="710">\033YGeschwaderführer\033X</t>
 <t id="711">Flügelmann</t>
 <t id="712">\033GEskorte\033X</t>
 <t id="713">\033WKein Ziel\033X</t>
 <t id="714">\033R%s\033X</t>
 <t id="715">\033B%s\033X</t>
 
 <t id="800">Trägerübersicht</t>
 <t id="801">\033WAusgewählt : \033X %s [%s]</t>
 <t id="802">\033WBefehle : \033X %s - \033WAutomatisiert :\033X %s</t>
 <t id="803">Auswahl</t>
 <t id="804">\033Y%s\033X [\033Y%s\033X] - Sektor : \033Y%s\033X</t>
 <t id="805">\033WStandort : \033X %s [%s]</t>
 <t id="806">Aktionen</t>
 <t id="807">Einstellen des ausgewählten Trägers</t>
 <t id="808">Aktuelle Einstellungen auf alle Träger anwenden</t>

 <t id="820">\033GJa\033X</t>
 <t id="821">\033RNein\033X</t>

<t id="001">** COMMENT ** v2.55 Begins Here</t>
 
 <t id="1000">ADS Setup Menu</t>
 <t id="1001">\033YSelected :\033X %s</t>
 <t id="1002">Manage Stations</t>
 <t id="1003">Manage Carriers</t>
 <t id="1004">\033YMenu\033X</t>
 <t id="1005">List ADS %ss</t>
 <t id="1006">Recent Events</t>
 <t id="1007">\033RUninstall ADS\033X</t>
 <t id="1008">Apply default settings to all %ss</t>
 <t id="1009">\033Y[\033X\033G%s\033X\033Y]\033X \033W%s\033X | auto: \033W%s\033X | Ships: \033W%s\033X</t>
 
 <t id="1010">\033RADS Manager\033X</t>
 <t id="1011">This menu gives you access to all \033YADS compatible\033X assets</t>
 <t id="1012">\033Y[\033X\033G%s\033X\033Y]\033X \033W%s\033X</t>
 <t id="1013">- \033GIntegrity:\033X Hull \033Y%s/100\033X - Shields \033Y%s/100\033X</t>
 <t id="1014">- \033GStatus:\033X \033W%s\033X - \033Y%s\033X</t>
 <t id="1015">- \033GCombat:\033X threat level \033Y%s\033X - attacked \033Y%s\033X - deployed \033Y%s\033X</t>
 <t id="1016">- \033GFighters:\033X  owned \033Y%s\033X - docked \033Y%s\033X - ADS \033Y%s\033X</t>
 <t id="1017">\033Y%s List\033X</t>
 <t id="1018">ADS Automated Mode  \033Y&lt;\033X \033W%s\033X \033Y&gt;\033X</t>
 <t id="1019">Open ADS %s setup menu</t>

 <t id="1020">\033Y[\033X\033G%s\033X\033Y]\033X \033G%s\033X | auto: \033W%s\033X | Ships: \033W%s\033X</t>
 <t id="1021">\033Y[\033X\033G%s\033X\033Y]\033X \033Y%s\033X | auto: \033W%s\033X | Ships: \033W%s\033X</t>
 <t id="1022">\033Y[\033X\033G%s\033X\033Y]\033X \033R%s\033X | auto: \033W%s\033X | Ships: \033W%s\033X</t>
 <t id="1023">\033G   Jump to Me</t>
 <t id="1024">\033G   Jump to Sector ...\033X</t>
 <t id="1025">\033G   Attack Target ...\033X</t>
 <t id="1026">Select Destination</t>
 <t id="1027">Select Target</t>
 <t id="1028">\033G   Patrol Sectors\033X</t>
 <t id="1029">\033G   Attack All\033X</t>

 <t id="1030">Select in crosshair and close</t>
 <t id="1031">%s deployed fighters in %s</t>
 <t id="1032">\033WReport From :\033X %s | \033WClass :\033X %s\n\033WLocation :\033X %s | \033WThreat Level :\033X %s\n\n\033WAction :\033X Fighters Launched</t>
 <t id="1033">\033G   Dock at ...\033X</t>
 <t id="1034">\033WCommand Panel\033X  \033Y&lt;\033G+\033X\033Y&gt;\033X</t>
 <t id="1035">View owned ships</t>
 <t id="1036">\033G   Protect ...\033X</t>
 <t id="1037">\033G   Standby\033X</t>
 <t id="1038">\033WCommand Panel\033X  \033Y&lt;\033G-\033X\033Y&gt;\033X</t>
 <t id="1039">\033G   %s\033G</t>
 
 <t id="1040">\033RADS:\033X \033WManager\033X</t>
 <t id="1041">\033W%s\033X  \033G[\033X%s\033G]\033X  \033G[\033X \033Whull\033X %s%% \033G|\033X \033Wshield\033X %s%% \033G]\033X</t>
 <t id="1042">Flying</t>
 <t id="1043">Docked</t>
 
<t id="001">** COMMENT ** v2.60 Begins Here</t>
 
 <t id="1044">Defense Grid</t>
 <t id="1045">General Settings</t>
 <t id="1046">Manage Sectors</t>
 <t id="1047">View Ships  \033Y&lt;\033X \033W%s\033X \033Y&gt;\033X</t>
 <t id="1048">ADS Satellite (%s)</t>
 <t id="1049">\033YDefense Grid\033X</t>
 
 <t id="1050">\033YSector List\033X</t>
 <t id="1051">[\033G%s,%s\033X] \033W%s\033X | Stations: \033G%s\033X | Threat Level: \033Y%s\033X</t>
 <t id="1052">Filter : %s</t>
 <t id="1053">All Sectors</t>
 <t id="1054">Sectors protected by ADS</t>
 <t id="1055">Threatened sectors</t>
 <t id="1056">\033YShip List\033X</t>
 <t id="1057">[\033G%s\033X] \033W%s\033X - \033W%s\033X | Defense Grid : \033Y%s\033X</t>
 <t id="1058">Defense Grid  \033Y&lt;\033X \033W%s\033X \033Y&gt;\033X</t>
 <t id="1059">Used by the Defense Grid  \033Y&lt;\033X \033W%s\033X \033Y&gt;\033X</t>
 
 <t id="1060">[\033G%s\033X] [%s]  \033W%s\033X</t>
 <t id="1061">\033WCommand Panel\033X</t>
 <t id="1062">\033GLaunch Wing\033X</t>
 <t id="1063">Change Target  \033Y&lt;\033X \033W%s\033X \033Y&gt;\033X</t>
 <t id="1064">Ship Count</t>
 <t id="1065">\033WManual Selection\033X</t>
 <t id="1066">\033G%s\033X</t>
 <t id="1067">\033Y%s\033X</t>
 <t id="1068">\033R%s\033X</t> 
 <t id="1069">Launch</t>
 
 <t id="1070">%s%%</t>
 <t id="1071">Stay Docked</t>
 <t id="1072">manual</t>
 <t id="1073">auto</t>
 <t id="1074">Class: %s | Owner: %s | Relation: %s</t>

 <t id="001">** COMMENT ** v2.65 Begins Here</t> 
 
 <t id="1075">Marine Training Center</t>
 <t id="1076">Crew Quarters</t>
 <t id="1077">Standard Training</t>
 <t id="1078">Combat Training</t>

<t id="001">** COMMENT ** Marine Statistics</t> 
 <t id="1079">  \033Y[\033X Fight: \033W%s\033X - Mech: \033W%s\033X - Hack: \033W%s\033X - Engineer: \033W%s\033X\033Y ]\033X</t>
 
 <t id="001">** COMMENT ** Marine Name - Overall Skill</t> 
 <t id="1080">\033G%s\033X - \033WOverall:\033X \033G%s\033X</t>

<t id="1081">Name</t>
 <t id="1082">Fightskill</t>
 <t id="1083">Mechanical</t>
 <t id="1084">Hacking</t>
 <t id="1085">Engineering</t>
 <t id="1086">Barracks ...</t>
 <t id="1087">\033GSave and close\033X</t>
 <t id="1088">\n\033RPress [Esc] to close without saving\033X</t>
 
 <t id="1089">\033WGeneral Settings\033X</t>
 <t id="1090">\033YDefault Setup\033X</t>
 <t id="1091">\033WEdit Default Carrier Setup\033W</t>
 <t id="1092">\033WEdit Default Station Setup\033W</t>
 <t id="1093">\033YDefense Grid Settings\033X</t>
 <t id="1094">\033WMaximum Jump Distance\033X</t>
 <t id="1095">\033WMinimum Threat to trigger an alert\033X</t>
 <t id="1096">\033WDisplay Warning Message\033X</t>
 <t id="1097">\033YIgnore Factions\033X</t>
 <t id="1098">\033YGeneral Settings\033X</t>
 <t id="1099">\033WDynamic Renaming System\033X</t>
 <t id="1100">\033RReset All Settings to default values\033X</t>
 <t id="1101">Auto</t>
 <t id="1102">Manual</t>
 <t id="1103">Trade Only</t>
 <t id="1104">Ignore</t>

<t id="1105">\033W- Training Cost :\033X \033Y%s\033X \033Wcredits per hour\033X</t>
<t id="1106">\033GApply Settings\033X</t>
<t id="1107">Barracks</t>
<t id="1108">\033W- There is %s marines training onboard\033X</t>
<t id="1109">\033W- Room :\033X \033Y%s/%s\033X</t>
<t id="1110">Passengers</t>
<t id="1111">Enslave</t>
<t id="1112">Train</t>
<t id="1113">\033RADS:\033X \033Y%s\033X \033Wis under attack [threat :\033X \033Y%s\033X\033W]\033X</t>
<t id="1114">[\033G%s,%s\033X] \033W%s:\033X \033G%s</t>
<t id="1115">%s\033X \033W%s\033X [\033Gauto\033X|\033W%s\033X]</t>
<t id="1116">%s\033X \033W%s\033X [\033Wmanual\033X|\033W%s\033X]</t>
<t id="1117">%s\033X \033W%s\033X</t>
<t id="1118">\033YGrid Members\033X</t>
<t id="1119">\033YUnassigned\033X</t>
<t id="1120">%s\033X \033W%s\033X [\033Ybattle\033X|\033W%s\033X]</t>
<t id="1121">[\033G%s,%s\033X] \033W%s:\033X \033Y%s</t>
<t id="1122">[\033G%s,%s\033X] \033W%s:\033X %s</t>
<t id="1123">\033Y%s\033X  \033G[\033X%s\033G]\033X  \033G[\033X \033Whull\033X %s%% \033G|\033X \033Wshield\033X %s%% \033G]\033X</t>

</page>

</language>

