<?xml version="1.0" standalone="yes"?>
<?xml-stylesheet href="x2script.xsl" type="text/xsl"?>
<!-- Generated using X-Studio -->

<script>
	<name>!init.glen.trade.ok</name>
	<version>1</version>
	<engineversion>44</engineversion>
	<description></description>
	<arguments />
	<sourcetext>
		<line linenr="001" indent="">
			<comment>* ******************************************************************************</comment>
		</line>
		<line linenr="002" indent="">
			<comment>* OK Trade</comment>
		</line>
		<line linenr="003" indent="">
			<comment>*  Existence of this script sets the game to modified allowing OK Trade to work</comment>
		</line>
		<line linenr="004" indent="">
			<comment>* ******************************************************************************</comment>
		</line>
		<line linenr="005" indent="" />
		<line linenr="006" indent="">
			<text>return</text>
			<text> </text>
			<var>null</var>
		</line>
	</sourcetext>
	<codearray>
		<sval type="array" size="10">
			<sval type="string" val="!init.glen.trade.ok" />
			<sval type="int" val="44" />
			<sval type="string" val="" />
			<sval type="int" val="1" />
			<sval type="int" val="0" />
			<sval type="int" val="0" />
			<sval type="array" size="1">
				<sval type="array" size="3">
					<sval type="int" val="103" />
					<sval type="int" val="0" />
					<sval type="int" val="0" />
				</sval>
			</sval>
			<sval type="int" val="0" />
			<sval type="array" size="5">
				<sval type="array" size="3">
					<sval type="int" val="0" />
					<sval type="int" val="1" />
					<sval type="string" val="******************************************************************************" />
				</sval>
				<sval type="array" size="3">
					<sval type="int" val="0" />
					<sval type="int" val="1" />
					<sval type="string" val="OK Trade" />
				</sval>
				<sval type="array" size="3">
					<sval type="int" val="0" />
					<sval type="int" val="1" />
					<sval type="string" val=" Existence of this script sets the game to modified allowing OK Trade to work" />
				</sval>
				<sval type="array" size="3">
					<sval type="int" val="0" />
					<sval type="int" val="1" />
					<sval type="string" val="******************************************************************************" />
				</sval>
				<sval type="array" size="2">
					<sval type="int" val="0" />
					<sval type="int" val="2" />
				</sval>
			</sval>
			<sval type="int" val="0" />
		</sval>
	</codearray>
</script>
